fdcodepy/__init__.py
fdcodepy/methods.py
fdcodepy/utils/__init__.py
fdcodepy/utils/helpers.py
fdcodepy-0.1.1.dist-info/LICENSE
fdcodepy-0.1.1.dist-info/METADATA
fdcodepy-0.1.1.dist-info/WHEEL
fdcodepy-0.1.1.dist-info/top_level.txt
fdcodepy-0.1.1.dist-info/RECORD
